geosot-0.1.0.dist-info/METADATA
geosot-0.1.0.dist-info/WHEEL
geosot/__init__.py
geosot/geosot.cp313-win_amd64.pyd
geosot-0.1.0.dist-info/RECORD
